[
  {
    "name": "help",
    "usage": ["help <command?/page?>", "? <command?/page?>"],
    "examples": ["help clear", "help 2"],
    "aliases": ["?"],
    "description": "Lists all of the commands available to the current user.",
    "callbackFunctionName": "help"
  },
  {
    "name": "clear",
    "usage": ["clear"],
    "examples": ["clear"],
    "aliases": [],
    "description": "Clears the terminal.",
    "callbackFunctionName": "clear"
  },
  {
    "name": "signin",
    "usage": ["signin"],
    "examples": ["signin"],
    "aliases": [],
    "description": "Redirects you to the sign in page.",
    "callbackFunctionName": "signin"
  },
  {
    "name": "signout",
    "usage": ["signout"],
    "examples": ["signout"],
    "aliases": [],
    "description": "Signs out the currently signed in user.",
    "callbackFunctionName": "signout"
  },
  {
    "name": "exit",
    "usage": ["exit"],
    "examples": ["exit"],
    "aliases": [],
    "description": "Closes the terminal window.",
    "callbackFunctionName": "exit"
  },
  {
    "name": "alias",
    "usage": ["alias", "alias name=value", "alias -u name"],
    "examples": ["alias", "alias ll=ls", "alias -u ll"],
    "aliases": [],
    "description": "Creates, lists, or removes command aliases.",
    "callbackFunctionName": "alias"
  },
  {
    "name": "export",
    "usage": ["export VAR=value", "export VAR"],
    "examples": ["export THIS=demo", "export PATH=/usr/bin"],
    "aliases": [],
    "description": "Sets environment variables for the terminal session.",
    "callbackFunctionName": "export"
  },
  {
    "name": "source",
    "usage": ["source [path]"],
    "examples": ["source ~/terminal_rc", "source /home/user/terminal_rc"],
    "aliases": ["."],
    "description": "Loads and executes commands from a script file.",
    "callbackFunctionName": "source"
  },
  {
    "name": "application",
    "usage": ["application <info/close/list> [uuid?]"],
    "examples": [
      "application info c2e69119-d46d-4e90-833a-d478b73c5b10",
      "application close cac7282a-fa26-41e1-9628-f58c25d0a533",
      "application list"
    ],
    "aliases": [],
    "description": "Closes an application or displays an application's info.",
    "callbackFunctionName": "application"
  },
  {
    "name": "reload",
    "usage": ["reload"],
    "examples": ["reload"],
    "aliases": [],
    "description": "Reloads the web page.",
    "callbackFunctionName": "reload"
  },
  {
    "name": "session",
    "usage": ["session <status/data>"],
    "examples": ["session status", "status data"],
    "aliases": [],
    "description": "Displays information about the authentication session.",
    "callbackFunctionName": "session"
  },
  {
    "name": "ls",
    "usage": ["ls [-la] [path]"],
    "examples": ["ls", "ls -la", "ls /home/user/Documents"],
    "aliases": [],
    "description": "Lists directory contents. Use -a to show hidden files, -l for long format.",
    "callbackFunctionName": "ls"
  },
  {
    "name": "cd",
    "usage": ["cd [path]"],
    "examples": ["cd", "cd /home/user", "cd ..", "cd ~/Documents"],
    "aliases": [],
    "description": "Changes the current working directory.",
    "callbackFunctionName": "cd"
  },
  {
    "name": "pwd",
    "usage": ["pwd"],
    "examples": ["pwd"],
    "aliases": [],
    "description": "Prints the current working directory.",
    "callbackFunctionName": "pwd"
  },
  {
    "name": "mkdir",
    "usage": ["mkdir [-p] <directory>"],
    "examples": ["mkdir test", "mkdir -p path/to/dir"],
    "aliases": [],
    "description": "Creates a new directory. Use -p to create parent directories as needed.",
    "callbackFunctionName": "mkdir"
  },
  {
    "name": "touch",
    "usage": ["touch <file>"],
    "examples": ["touch newfile.txt", "touch /home/user/test.md"],
    "aliases": [],
    "description": "Creates an empty file or updates file timestamps.",
    "callbackFunctionName": "touch"
  },
  {
    "name": "rm",
    "usage": ["rm [-rf] <file/directory>"],
    "examples": ["rm file.txt", "rm -r folder", "rm -rf folder"],
    "aliases": [],
    "description": "Removes files or directories. Use -r for directories, -f to force.",
    "callbackFunctionName": "rm"
  },
  {
    "name": "cat",
    "usage": ["cat <file>"],
    "examples": ["cat readme.txt", "cat /home/user/.bashrc"],
    "aliases": [],
    "description": "Displays the contents of a file.",
    "callbackFunctionName": "cat"
  }
]
